README.txt
setup.cfg
setup.py
collective/__init__.py
collective.portlet.bookmarks.egg-info/PKG-INFO
collective.portlet.bookmarks.egg-info/SOURCES.txt
collective.portlet.bookmarks.egg-info/dependency_links.txt
collective.portlet.bookmarks.egg-info/entry_points.txt
collective.portlet.bookmarks.egg-info/namespace_packages.txt
collective.portlet.bookmarks.egg-info/not-zip-safe
collective.portlet.bookmarks.egg-info/requires.txt
collective.portlet.bookmarks.egg-info/top_level.txt
collective/portlet/__init__.py
collective/portlet/bookmarks/__init__.py
collective/portlet/bookmarks/bookmarks.py
collective/portlet/bookmarks/bookmarksportlet.pt
collective/portlet/bookmarks/bookmarksportlet.py
collective/portlet/bookmarks/configure.zcml
collective/portlet/bookmarks/usei18ndude.sh
collective/portlet/bookmarks/kss/bookmarks.kss
collective/portlet/bookmarks/locales/collective.portlet.bookmarks.pot
collective/portlet/bookmarks/locales/cs/LC_MESSAGES/collective.portlet.bookmarks.po
collective/portlet/bookmarks/locales/en/LC_MESSAGES/collective.portlet.bookmarks.po
collective/portlet/bookmarks/profiles/default/kssregistry.xml
collective/portlet/bookmarks/profiles/default/metadata.xml
collective/portlet/bookmarks/profiles/default/portlets.xml
collective/portlet/bookmarks/tests/__init__.py
collective/portlet/bookmarks/tests/base.py
collective/portlet/bookmarks/tests/test_portlet.py
docs/HISTORY.txt
docs/INSTALL.txt
docs/LICENSE.GPL
docs/LICENSE.txt