Metadata-Version: 1.0
Name: collective.portlet.bookmarks
Version: 0.1
Summary: A portlet that allows users to bookmark pages in a site
Home-page: http://plone.org
Author: Netsight Internet Solutions
Author-email: matth@netsight.co.uk
License: GPL
Keywords: plone bookmarks favorites portlet kss
Platform: UNKNOWN
Classifier: Framework :: Plone
Classifier: Framework :: Zope2
Classifier: Framework :: Zope3
Classifier: Programming Language :: Python
Classifier: Topic :: Software Development :: Libraries :: Python Modules
